seaflowpy/__init__.py
seaflowpy/db.py
seaflowpy/errors.py
seaflowpy/fileio.py
seaflowpy/filterevt.py
seaflowpy/geo.py
seaflowpy/particleops.py
seaflowpy/plan.py
seaflowpy/py.typed
seaflowpy/sample.py
seaflowpy/seaflowfile.py
seaflowpy/sfl.py
seaflowpy/time.py
seaflowpy/util.py
seaflowpy/vct.py
seaflowpy/cli/__init__.py
seaflowpy/cli/commands/__init__.py
seaflowpy/cli/commands/dayofyear_cmd.py
seaflowpy/cli/commands/db_cmd.py
seaflowpy/cli/commands/evt_cmd.py
seaflowpy/cli/commands/filter_cmd.py
seaflowpy/cli/commands/opp_cmd.py
seaflowpy/cli/commands/sds2sfl_cmd.py
seaflowpy/cli/commands/sfl_cmd.py
seaflowpy/cli/commands/vct_cmd.py
seaflowpy/cli/commands/version_cmd.py
seaflowpy/data/popcycle.sql
seaflowpy-14.6.0.dist-info/METADATA
seaflowpy-14.6.0.dist-info/WHEEL
seaflowpy-14.6.0.dist-info/entry_points.txt
seaflowpy-14.6.0.dist-info/licenses/LICENSE
seaflowpy-14.6.0.dist-info/RECORD
