Metadata-Version: 2.4
Name: seaflowpy
Version: 14.6.0
Summary: A Python library for SeaFlow data
Author-email: "Chris T. Berthiaume" <chrisbee@uw.edu>
License-Expression: MIT
License-File: LICENSE
Requires-Python: >=3.10
Requires-Dist: click>=8.1.8
Requires-Dist: joblib~=1.4.2
Requires-Dist: pandas[performance]~=2.2
Requires-Dist: psutil>=6.1.1
Requires-Dist: pyarrow>=19.0.0
Requires-Dist: sqlalchemy>=2.0.38
Requires-Dist: tqdm>=4.67.1
Requires-Dist: tsdataformat>=3.1.1
Requires-Dist: zstandard>=0.23.0
